{"00daca0d-cf74-468e-a90a-9a4a5b06316c":{"id":"00daca0d-cf74-468e-a90a-9a4a5b06316c","name":{"first":"Martin","last":"Atkinson","display":"Martin Atkinson"},"appearances":348,"yellowCards":1140,"redCards":52,"debut":"2004-09-18T15:00:00+01:00","alternativeIds":{"opta":"o18757","premierLeagueId":"16951"}},"34c07554-5136-4e9d-8be2-51cd8cadf483":{"id":"34c07554-5136-4e9d-8be2-51cd8cadf483","name":{"first":"Lee","last":"Mason","display":"Lee Mason"},"appearances":216,"yellowCards":654,"redCards":34,"debut":"2006-02-04T15:00:00Z","alternativeIds":{"opta":"o28689","premierLeagueId":"16954"}},"36046934-ebfb-47ba-b8d7-a2669e1478df":{"id":"36046934-ebfb-47ba-b8d7-a2669e1478df","name":{"first":"Anthony","last":"Taylor","display":"Anthony Taylor"},"appearances":146,"yellowCards":484,"redCards":25,"debut":"2010-02-03T20:00:00Z","alternativeIds":{"opta":"o40933","premierLeagueId":"16961"}},"374cc1b9-33e1-434e-a938-dda44d0c463a":{"id":"374cc1b9-33e1-434e-a938-dda44d0c463a","name":{"first":"Craig","last":"Pawson","display":"Craig Pawson"},"appearances":67,"yellowCards":208,"redCards":10,"debut":"2013-03-02T15:00:00Z","alternativeIds":{"opta":"o41051","premierLeagueId":"16967"}},"49058053-ce8f-40eb-b957-900a97f11da1":{"id":"49058053-ce8f-40eb-b957-900a97f11da1","name":{"first":"Neil","last":"Swarbrick","display":"Neil Swarbrick"},"appearances":95,"yellowCards":326,"redCards":10,"debut":"2010-12-11T15:00:00Z","alternativeIds":{"opta":"o40923","premierLeagueId":"16965"}},"634fdb60-91a7-439a-b067-08e9a3f5d5ab":{"id":"634fdb60-91a7-439a-b067-08e9a3f5d5ab","name":{"first":"Stuart","last":"Attwell","display":"Stuart Attwell"},"appearances":52,"yellowCards":176,"redCards":10,"debut":"2008-08-23T15:00:00+01:00","alternativeIds":{"opta":"o40959","premierLeagueId":"16960"}},"662feed8-54de-472d-b5cd-4fa36f763fdc":{"id":"662feed8-54de-472d-b5cd-4fa36f763fdc","name":{"first":"Paul","last":"Tierney","display":"Paul Tierney"},"appearances":7,"yellowCards":20,"redCards":0,"debut":"2013-08-06T19:45:00+01:00","alternativeIds":{"opta":"o41180","premierLeagueId":"17019"}},"6b1b91d8-cfa9-4f20-be41-a39c7a4cd94e":{"id":"6b1b91d8-cfa9-4f20-be41-a39c7a4cd94e","name":{"first":"Kevin","last":"Friend","display":"Kevin Friend"},"appearances":143,"yellowCards":521,"redCards":19,"debut":"2009-09-20T14:00:00+01:00","alternativeIds":{"opta":"o40928","premierLeagueId":"16962"}},"85c9134f-7228-4184-beb5-dd6713a5abda":{"id":"85c9134f-7228-4184-beb5-dd6713a5abda","name":{"first":"Mike","last":"Dean","display":"Mike Dean"},"appearances":624,"yellowCards":2184,"redCards":127,"debut":"2000-09-09T15:00:00+01:00","alternativeIds":{"opta":"o10508","premierLeagueId":"16941"}},"995c9355-c0cf-4475-81bc-3ddab16b486c":{"id":"995c9355-c0cf-4475-81bc-3ddab16b486c","name":{"first":"Mark","last":"Clattenburg","display":"Mark Clattenburg"},"appearances":344,"yellowCards":1114,"redCards":52,"debut":"2004-08-21T15:00:00+01:00","alternativeIds":{"opta":"o18487","premierLeagueId":"16949"}},"a6a27c20-6825-4162-9a8c-505c54cf60b5":{"id":"a6a27c20-6825-4162-9a8c-505c54cf60b5","name":{"first":"Andy","last":"Taylor","display":"Andy Taylor"},"appearances":0,"yellowCards":0,"redCards":0,"debut":"2016-11-05T15:00:00Z","alternativeIds":{"opta":"o48433","premierLeagueId":"21322"}},"acb6ea21-31ac-4a72-8667-655a8aa0f8cf":{"id":"acb6ea21-31ac-4a72-8667-655a8aa0f8cf","name":{"first":"Mike","last":"Jones","display":"Mike Jones"},"appearances":188,"yellowCards":573,"redCards":25,"debut":"1994-08-27T15:00:00+01:00","alternativeIds":{"opta":"o40921","premierLeagueId":"16922"}},"bf16c3d2-be00-49a7-8211-df9a3137d23c":{"id":"bf16c3d2-be00-49a7-8211-df9a3137d23c","name":{"first":"Jonathan","last":"Moss","display":"Jonathan Moss"},"appearances":123,"yellowCards":402,"redCards":21,"debut":"2011-01-04T20:00:00Z","alternativeIds":{"opta":"o40936","premierLeagueId":"16964"}},"c2bd3b02-c933-48ce-8547-693bbf4ee05a":{"id":"c2bd3b02-c933-48ce-8547-693bbf4ee05a","name":{"first":"Andre","last":"Marriner","display":"Andre Marriner"},"appearances":256,"yellowCards":819,"redCards":49,"debut":"2004-11-13T15:00:00Z","alternativeIds":{"opta":"o19485","premierLeagueId":"16950"}},"f2ed6c36-9cc4-4b21-9acf-3433a330b314":{"id":"f2ed6c36-9cc4-4b21-9acf-3433a330b314","name":{"first":"Michael","last":"Oliver","display":"Michael Oliver"},"appearances":150,"yellowCards":480,"redCards":20,"debut":"2010-08-21T15:00:00+01:00","alternativeIds":{"opta":"o40962","premierLeagueId":"16963"}},"f4c9b702-a341-4e13-be3c-8feb3a818809":{"id":"f4c9b702-a341-4e13-be3c-8feb3a818809","name":{"first":"Graham","last":"Scott","display":"Graham Scott"},"appearances":7,"yellowCards":31,"redCards":1,"debut":"2013-08-27T19:45:00+01:00","alternativeIds":{"opta":"o41049","premierLeagueId":"16989"}},"f84b506c-1d6a-4c87-80a0-ca615368a408":{"id":"f84b506c-1d6a-4c87-80a0-ca615368a408","name":{"first":"Roger","last":"East","display":"Roger East"},"appearances":57,"yellowCards":171,"redCards":9,"debut":"2012-09-01T15:00:00+01:00","alternativeIds":{"opta":"o40961","premierLeagueId":"16966"}},"fa0bd4bb-b72f-41e4-925f-31c2c22eece8":{"id":"fa0bd4bb-b72f-41e4-925f-31c2c22eece8","name":{"first":"Robert","last":"Madley","display":"Robert Madley"},"appearances":52,"yellowCards":163,"redCards":9,"debut":"2013-04-27T15:00:00+01:00","alternativeIds":{"opta":"o41412","premierLeagueId":"16968"}}}